bytedance_easy_rc_doc/__init__.py
bytedance_easy_rc_doc-0.0.1.dist-info/METADATA
bytedance_easy_rc_doc-0.0.1.dist-info/WHEEL
bytedance_easy_rc_doc-0.0.1.dist-info/top_level.txt
bytedance_easy_rc_doc-0.0.1.dist-info/RECORD
